periodic_tasks/__init__.py
periodic_tasks/periodic_tasks.py
periodic_tasks/py.typed
periodic_tasks-0.1.1.dist-info/METADATA
periodic_tasks-0.1.1.dist-info/WHEEL
periodic_tasks-0.1.1.dist-info/top_level.txt
periodic_tasks-0.1.1.dist-info/RECORD
