Metadata-Version: 2.1
Name: periodic_tasks
Version: 0.1.1
Summary: Single-thread interval scheduler
Author-email: Aleksander Veksler <aleksve@gmail.com>
License: MIT
Project-URL: Bug Tracker, https://github.com/aleksve/periodic_tasks/issues
Project-URL: homepage, https://github.com/aleksve/periodic_tasks
Classifier: Programming Language :: Python :: 3
Classifier: License :: OSI Approved :: MIT License
Classifier: Operating System :: OS Independent
Requires-Python: >=3.10
